diebohnen/__init__.py
diebohnen/common.py
diebohnen/diebohnen.py
DieBohnen-0.0.3.dist-info/LICENSE
DieBohnen-0.0.3.dist-info/METADATA
DieBohnen-0.0.3.dist-info/WHEEL
DieBohnen-0.0.3.dist-info/entry_points.txt
DieBohnen-0.0.3.dist-info/top_level.txt
DieBohnen-0.0.3.dist-info/RECORD
